multigitlib/__init__.py
multigitlib/__main__.py
multigitlib/subrepo.py
multigit_lib-0.0.1.post2.dist-info/METADATA
multigit_lib-0.0.1.post2.dist-info/WHEEL
multigit_lib-0.0.1.post2.dist-info/licenses/LICENSE
multigit_lib-0.0.1.post2.dist-info/RECORD
